perm_test_rust-0.3.3.dist-info/METADATA
perm_test_rust-0.3.3.dist-info/WHEEL
perm_test_rust-0.3.3.dist-info/licenses/LICENSE
perm_test/__init__.py
perm_test/perm_test.cpython-38-s390x-linux-gnu.so
perm_test_rust-0.3.3.dist-info/RECORD
