Metadata-Version: 2.4
Name: perm_test_rust
Version: 0.3.3
Classifier: Programming Language :: Rust
Classifier: Programming Language :: Python :: Implementation :: CPython
Classifier: Programming Language :: Python :: Implementation :: PyPy
License-File: LICENSE
Summary: A rust implementation for fast permutation testing
Author-email: Puck van Gijzen <puckvangijzen@proton.me>
License: MIT
Requires-Python: >=3.8
Project-URL: Homepage, https://github.com/puncks/perm_test
Project-URL: Issues, https://github.com/puncks/perm_test/issues
